aros_node/__init__.py
aros_node/data_loader.py
aros_node/evaluate.py
aros_node/stability_loss_function.py
aros_node/utils.py
aros_node/version.py
aros_node-0.0.1.dist-info/LICENSE
aros_node-0.0.1.dist-info/METADATA
aros_node-0.0.1.dist-info/WHEEL
aros_node-0.0.1.dist-info/top_level.txt
aros_node-0.0.1.dist-info/RECORD
