Metadata-Version: 2.2
Name: aros-node
Version: 0.0.1
Summary: AROS: Adversarially Robust Out-of-Distribution Detection through Stability
Home-page: https://github.com/AdaptiveMotorControlLab/AROS
Author: Hossein Mirzaei, Mackenzie Mathis
Author-email: mackenzie@post.harvard.edu
Requires-Python: >=3.10
License-File: LICENSE
Requires-Dist: geotorch
Requires-Dist: torch
Requires-Dist: torchdiffeq
Requires-Dist: timm==1.0.9
Requires-Dist: robustbench
Requires-Dist: numpy
Requires-Dist: scikit-learn
Requires-Dist: scipy
Requires-Dist: tqdm
Provides-Extra: dev
Requires-Dist: pylint; extra == "dev"
Requires-Dist: toml; extra == "dev"
Requires-Dist: yapf; extra == "dev"
Requires-Dist: black; extra == "dev"
Requires-Dist: pytest; extra == "dev"
